{"resourceType":"Observation","id":"ca3f590f-86d4-5c8b-ba9b-329246918231","status":"final","category":{"coding":[{"system":"http://hl7.org/fhir/observation-category","code":"laboratory","display":"Laboratory"}]},"code":{"coding":[{"system":"http://loinc.org","code":"6768-6","display":"Alkaline phosphatase [Enzymatic activity/volume] i"}]},"subject":{"reference":"https://dev-api.va.gov/services/fhir/v0/dstu2/Patient/17000098","display":"Mr. Freeman822 Prohaska837"},"effectiveDateTime":"2014-09-06T09:19:58Z","issued":"2014-09-06T09:19:58Z","performer":[],"valueQuantity":{"value":80.59560713573373,"unit":"U/L","system":"http://unitsofmeasure.org","code":"U/L"}}