{"objectType":"DiagnosticReport","objectVersion":0,"fullIcn":"17000098","patientName":"Mr. Freeman822 Prohaska837","DiagnosticReports":[{"identifier":"17003858:L","effectiveDateTime":"2008-09-13T09:19:58Z","issuedDateTime":"2008-09-13T09:19:58Z","accessionInstitutionSid":"457959:I","accessionInstitutionName":"LYONS VA MEDICAL CENTER","results":[{"result":"17030596:L","display":"Glucose"},{"result":"17030597:L","display":"Urea Nitrogen"},{"result":"17030598:L","display":"Creatinine"},{"result":"17030599:L","display":"Calcium"},{"result":"17030600:L","display":"Sodium"},{"result":"17030601:L","display":"Potassium"},{"result":"17030602:L","display":"Chloride"},{"result":"17030603:L","display":"Carbon Dioxide"}]}]}