{"resourceType":"Bundle","type":"searchset","total":6822,"link":[{"relation":"first","url":"https://dev-api.va.gov/services/fhir/v0/dstu2/Observation?patient=25000285&page=1&_count=15"},{"relation":"prev","url":"https://dev-api.va.gov/services/fhir/v0/dstu2/Observation?patient=25000285&page=185&_count=15"},{"relation":"self","url":"https://dev-api.va.gov/services/fhir/v0/dstu2/Observation?patient=25000285&page=186&_count=15"},{"relation":"next","url":"https://dev-api.va.gov/services/fhir/v0/dstu2/Observation?patient=25000285&page=187&_count=15"},{"relation":"last","url":"https://dev-api.va.gov/services/fhir/v0/dstu2/Observation?patient=25000285&page=455&_count=15"}],"entry":[{"fullUrl":"https://dev-api.va.gov/services/fhir/v0/dstu2/Observation/180235c9-3faa-5263-8aab-ccf0e22f5fde","resource":{"resourceType":"Observation","id":"180235c9-3faa-5263-8aab-ccf0e22f5fde","status":"final","category":{"coding":[{"system":"http://hl7.org/fhir/observation-category","code":"laboratory","display":"Laboratory"}]},"code":{"coding":[{"system":"http://loinc.org","code":"2514-8","display":"Ketones [Presence] in Urine by Test strip"}]},"subject":{"reference":"https://dev-api.va.gov/services/fhir/v0/dstu2/Patient/25000285","display":"Mr. Porfirio146 Schmeler639"},"effectiveDateTime":"2005-10-27T04:39:20Z","issued":"2005-10-27T04:39:20Z","performer":[]},"search":{"mode":"match"}},{"fullUrl":"https://dev-api.va.gov/services/fhir/v0/dstu2/Observation/7582dc26-88ab-560d-8853-9dd0addf12a1","resource":{"resourceType":"Observation","id":"7582dc26-88ab-560d-8853-9dd0addf12a1","status":"final","category":{"coding":[{"system":"http://hl7.org/fhir/observation-category","code":"laboratory","display":"Laboratory"}]},"code":{"coding":[{"system":"http://loinc.org","code":"5797-6","display":"Ketones [Mass/volume] in Urine by Test strip"}]},"subject":{"reference":"https://dev-api.va.gov/services/fhir/v0/dstu2/Patient/25000285","display":"Mr. Porfirio146 Schmeler639"},"effectiveDateTime":"2005-10-27T04:39:20Z","issued":"2005-10-27T04:39:20Z","performer":[],"valueQuantity":{"value":16.992258825620596,"unit":"mg/dL","system":"http://unitsofmeasure.org","code":"mg/dL"}},"search":{"mode":"match"}},{"fullUrl":"https://dev-api.va.gov/services/fhir/v0/dstu2/Observation/2c6954fc-0e24-57ea-8992-d93c74f829be","resource":{"resourceType":"Observation","id":"2c6954fc-0e24-57ea-8992-d93c74f829be","status":"final","category":{"coding":[{"system":"http://hl7.org/fhir/observation-category","code":"laboratory","display":"Laboratory"}]},"code":{"coding":[{"system":"http://loinc.org","code":"5770-3","display":"Bilirubin.total [Presence] in Urine by Test strip"}]},"subject":{"reference":"https://dev-api.va.gov/services/fhir/v0/dstu2/Patient/25000285","display":"Mr. Porfirio146 Schmeler639"},"effectiveDateTime":"2005-10-27T04:39:20Z","issued":"2005-10-27T04:39:20Z","performer":[]},"search":{"mode":"match"}},{"fullUrl":"https://dev-api.va.gov/services/fhir/v0/dstu2/Observation/5432666b-3d69-5016-a562-937e8fd1893b","resource":{"resourceType":"Observation","id":"5432666b-3d69-5016-a562-937e8fd1893b","status":"final","category":{"coding":[{"system":"http://hl7.org/fhir/observation-category","code":"laboratory","display":"Laboratory"}]},"code":{"coding":[{"system":"http://loinc.org","code":"20505-4","display":"Bilirubin.total [Mass/volume] in Urine by Test str"}]},"subject":{"reference":"https://dev-api.va.gov/services/fhir/v0/dstu2/Patient/25000285","display":"Mr. Porfirio146 Schmeler639"},"effectiveDateTime":"2005-10-27T04:39:20Z","issued":"2005-10-27T04:39:20Z","performer":[],"valueQuantity":{"value":1.1261112465436445,"unit":"mg/dL","system":"http://unitsofmeasure.org","code":"mg/dL"}},"search":{"mode":"match"}},{"fullUrl":"https://dev-api.va.gov/services/fhir/v0/dstu2/Observation/01c1d84f-ed0f-58de-9771-ae5056b3ffc4","resource":{"resourceType":"Observation","id":"01c1d84f-ed0f-58de-9771-ae5056b3ffc4","status":"final","category":{"coding":[{"system":"http://hl7.org/fhir/observation-category","code":"laboratory","display":"Laboratory"}]},"code":{"coding":[{"system":"http://loinc.org","code":"25428-4","display":"Glucose [Presence] in Urine by Test strip"}]},"subject":{"reference":"https://dev-api.va.gov/services/fhir/v0/dstu2/Patient/25000285","display":"Mr. Porfirio146 Schmeler639"},"effectiveDateTime":"2005-10-27T04:39:20Z","issued":"2005-10-27T04:39:20Z","performer":[]},"search":{"mode":"match"}},{"fullUrl":"https://dev-api.va.gov/services/fhir/v0/dstu2/Observation/02b8524e-9e68-5ef8-bb89-0ac8bd569639","resource":{"resourceType":"Observation","id":"02b8524e-9e68-5ef8-bb89-0ac8bd569639","status":"final","category":{"coding":[{"system":"http://hl7.org/fhir/observation-category","code":"laboratory","display":"Laboratory"}]},"code":{"coding":[{"system":"http://loinc.org","code":"5792-7","display":"Glucose [Mass/volume] in Urine by Test strip"}]},"subject":{"reference":"https://dev-api.va.gov/services/fhir/v0/dstu2/Patient/25000285","display":"Mr. Porfirio146 Schmeler639"},"effectiveDateTime":"2005-10-27T04:39:20Z","issued":"2005-10-27T04:39:20Z","performer":[],"valueQuantity":{"value":1.4395802335703352,"unit":"mg/dL","system":"http://unitsofmeasure.org","code":"mg/dL"}},"search":{"mode":"match"}},{"fullUrl":"https://dev-api.va.gov/services/fhir/v0/dstu2/Observation/698dd3c6-a047-57d6-b8f5-d9fcd12347ef","resource":{"resourceType":"Observation","id":"698dd3c6-a047-57d6-b8f5-d9fcd12347ef","status":"final","category":{"coding":[{"system":"http://hl7.org/fhir/observation-category","code":"laboratory","display":"Laboratory"}]},"code":{"coding":[{"system":"http://loinc.org","code":"5778-6","display":"Color of Urine"}]},"subject":{"reference":"https://dev-api.va.gov/services/fhir/v0/dstu2/Patient/25000285","display":"Mr. Porfirio146 Schmeler639"},"effectiveDateTime":"2005-10-27T04:39:20Z","issued":"2005-10-27T04:39:20Z","performer":[]},"search":{"mode":"match"}},{"fullUrl":"https://dev-api.va.gov/services/fhir/v0/dstu2/Observation/1862d200-b794-54cc-9700-fb202707b979","resource":{"resourceType":"Observation","id":"1862d200-b794-54cc-9700-fb202707b979","status":"final","category":{"coding":[{"system":"http://hl7.org/fhir/observation-category","code":"laboratory","display":"Laboratory"}]},"code":{"coding":[{"system":"http://loinc.org","code":"32167-9","display":"Clarity of Urine"}]},"subject":{"reference":"https://dev-api.va.gov/services/fhir/v0/dstu2/Patient/25000285","display":"Mr. Porfirio146 Schmeler639"},"effectiveDateTime":"2005-10-27T04:39:20Z","issued":"2005-10-27T04:39:20Z","performer":[]},"search":{"mode":"match"}},{"fullUrl":"https://dev-api.va.gov/services/fhir/v0/dstu2/Observation/4c54f709-4d14-5007-9a57-7797d8f88e43","resource":{"resourceType":"Observation","id":"4c54f709-4d14-5007-9a57-7797d8f88e43","status":"final","category":{"coding":[{"system":"http://hl7.org/fhir/observation-category","code":"laboratory","display":"Laboratory"}]},"code":{"coding":[{"system":"http://loinc.org","code":"5767-9","display":"Appearance of Urine"}]},"subject":{"reference":"https://dev-api.va.gov/services/fhir/v0/dstu2/Patient/25000285","display":"Mr. Porfirio146 Schmeler639"},"effectiveDateTime":"2005-10-27T04:39:20Z","issued":"2005-10-27T04:39:20Z","performer":[]},"search":{"mode":"match"}},{"fullUrl":"https://dev-api.va.gov/services/fhir/v0/dstu2/Observation/5acbd3ab-684b-529e-9fe2-5617a00e48c3","resource":{"resourceType":"Observation","id":"5acbd3ab-684b-529e-9fe2-5617a00e48c3","status":"final","category":{"coding":[{"system":"http://hl7.org/fhir/observation-category","code":"laboratory","display":"Laboratory"}]},"code":{"coding":[{"system":"http://loinc.org","code":"5767-9","display":"Appearance of Urine"}]},"subject":{"reference":"https://dev-api.va.gov/services/fhir/v0/dstu2/Patient/25000285","display":"Mr. Porfirio146 Schmeler639"},"effectiveDateTime":"2005-10-27T04:39:20Z","issued":"2005-10-27T04:39:20Z","performer":[]},"search":{"mode":"match"}},{"fullUrl":"https://dev-api.va.gov/services/fhir/v0/dstu2/Observation/e2d4b17d-bd5d-5498-a80a-7f6ccebf6c6a","resource":{"resourceType":"Observation","id":"e2d4b17d-bd5d-5498-a80a-7f6ccebf6c6a","status":"final","category":{"coding":[{"system":"http://hl7.org/fhir/observation-category","code":"laboratory","display":"Laboratory"}]},"code":{"coding":[{"system":"http://loinc.org","code":"1920-8","display":"Aspartate aminotransferase [Enzymatic activity/vol"}]},"subject":{"reference":"https://dev-api.va.gov/services/fhir/v0/dstu2/Patient/25000285","display":"Mr. Porfirio146 Schmeler639"},"effectiveDateTime":"2005-10-27T04:39:20Z","issued":"2005-10-27T04:39:20Z","performer":[],"valueQuantity":{"value":35.152786781212455,"unit":"U/L","system":"http://unitsofmeasure.org","code":"U/L"}},"search":{"mode":"match"}},{"fullUrl":"https://dev-api.va.gov/services/fhir/v0/dstu2/Observation/5ff6b2af-cbee-560f-9360-e57baf967ab1","resource":{"resourceType":"Observation","id":"5ff6b2af-cbee-560f-9360-e57baf967ab1","status":"final","category":{"coding":[{"system":"http://hl7.org/fhir/observation-category","code":"laboratory","display":"Laboratory"}]},"code":{"coding":[{"system":"http://loinc.org","code":"1742-6","display":"Alanine aminotransferase [Enzymatic activity/volum"}]},"subject":{"reference":"https://dev-api.va.gov/services/fhir/v0/dstu2/Patient/25000285","display":"Mr. Porfirio146 Schmeler639"},"effectiveDateTime":"2005-10-27T04:39:20Z","issued":"2005-10-27T04:39:20Z","performer":[],"valueQuantity":{"value":32.21171511075324,"unit":"U/L","system":"http://unitsofmeasure.org","code":"U/L"}},"search":{"mode":"match"}},{"fullUrl":"https://dev-api.va.gov/services/fhir/v0/dstu2/Observation/b12bd38c-8063-5d86-a5f8-4a7143111564","resource":{"resourceType":"Observation","id":"b12bd38c-8063-5d86-a5f8-4a7143111564","status":"final","category":{"coding":[{"system":"http://hl7.org/fhir/observation-category","code":"laboratory","display":"Laboratory"}]},"code":{"coding":[{"system":"http://loinc.org","code":"6768-6","display":"Alkaline phosphatase [Enzymatic activity/volume] i"}]},"subject":{"reference":"https://dev-api.va.gov/services/fhir/v0/dstu2/Patient/25000285","display":"Mr. Porfirio146 Schmeler639"},"effectiveDateTime":"2005-10-27T04:39:20Z","issued":"2005-10-27T04:39:20Z","performer":[],"valueQuantity":{"value":130.3147335785315,"unit":"U/L","system":"http://unitsofmeasure.org","code":"U/L"}},"search":{"mode":"match"}},{"fullUrl":"https://dev-api.va.gov/services/fhir/v0/dstu2/Observation/91eeb80d-006b-545a-8f97-e4b8fc03b368","resource":{"resourceType":"Observation","id":"91eeb80d-006b-545a-8f97-e4b8fc03b368","status":"final","category":{"coding":[{"system":"http://hl7.org/fhir/observation-category","code":"laboratory","display":"Laboratory"}]},"code":{"coding":[{"system":"http://loinc.org","code":"1975-2","display":"Bilirubin.total [Mass/volume] in Serum or Plasma"}]},"subject":{"reference":"https://dev-api.va.gov/services/fhir/v0/dstu2/Patient/25000285","display":"Mr. Porfirio146 Schmeler639"},"effectiveDateTime":"2005-10-27T04:39:20Z","issued":"2005-10-27T04:39:20Z","performer":[],"valueQuantity":{"value":0.21782199778566208,"unit":"mg/dL","system":"http://unitsofmeasure.org","code":"mg/dL"}},"search":{"mode":"match"}},{"fullUrl":"https://dev-api.va.gov/services/fhir/v0/dstu2/Observation/b27b5904-3cb2-5b40-96cf-28df9cca4a20","resource":{"resourceType":"Observation","id":"b27b5904-3cb2-5b40-96cf-28df9cca4a20","status":"final","category":{"coding":[{"system":"http://hl7.org/fhir/observation-category","code":"laboratory","display":"Laboratory"}]},"code":{"coding":[{"system":"http://loinc.org","code":"10834-0","display":"Globulin [Mass/volume] in Serum by calculation"}]},"subject":{"reference":"https://dev-api.va.gov/services/fhir/v0/dstu2/Patient/25000285","display":"Mr. Porfirio146 Schmeler639"},"effectiveDateTime":"2005-10-27T04:39:20Z","issued":"2005-10-27T04:39:20Z","performer":[],"valueQuantity":{"value":2.4722319705953613,"unit":"g/L","system":"http://unitsofmeasure.org","code":"g/L"}},"search":{"mode":"match"}}]}