{"objectType":"Observation","objectVersion":1,"cdwId":"597:L","status":"final","category":"laboratory","code":{"coding":{"system":"http://loinc.org","code":"2085-9","display":"High Density Lipoprotein Cholesterol"}},"subject":{"type":"Patient","reference":"9","display":"Mr. Titus37 Mosciski958"},"effectiveDateTime":"2006-05-17T23:37:51Z","issued":"2006-05-17T23:37:51Z","performer":[{"type":"Organization","reference":"561596:I","display":"NEW AMSTERDAM CBOC"},{"type":"Practitioner","reference":"305693","display":"DR. THOMAS359 REYNOLDS206 PHD"}],"valueQuantity":{"value":57.752047587496065,"unit":"mg/dL","system":"http://unitsofmeasure.org","code":"mg/dL"}}