{"resourceType":"Observation","id":"65fec134-ae18-5957-84fe-90cc7834c9fd","status":"final","category":{"coding":[{"system":"http://hl7.org/fhir/observation-category","code":"laboratory","display":"Laboratory"}]},"code":{"coding":[{"system":"http://loinc.org","code":"2947-0","display":"Sodium"}]},"subject":{"reference":"https://dev-api.va.gov/services/fhir/v0/dstu2/Patient/2000167","display":"Mr. Jefferey580 Terry864"},"effectiveDateTime":"2016-05-02T09:14:31Z","issued":"2016-05-02T09:14:31Z","performer":[],"valueQuantity":{"value":137.94931622048549,"unit":"mmol/L","system":"http://unitsofmeasure.org","code":"mmol/L"}}