{"resourceType":"Bundle","type":"searchset","total":6837,"link":[{"relation":"first","url":"https://dev-api.va.gov/services/fhir/v0/dstu2/Observation?patient=5000335&page=1&_count=15"},{"relation":"prev","url":"https://dev-api.va.gov/services/fhir/v0/dstu2/Observation?patient=5000335&page=351&_count=15"},{"relation":"self","url":"https://dev-api.va.gov/services/fhir/v0/dstu2/Observation?patient=5000335&page=352&_count=15"},{"relation":"next","url":"https://dev-api.va.gov/services/fhir/v0/dstu2/Observation?patient=5000335&page=353&_count=15"},{"relation":"last","url":"https://dev-api.va.gov/services/fhir/v0/dstu2/Observation?patient=5000335&page=456&_count=15"}],"entry":[{"fullUrl":"https://dev-api.va.gov/services/fhir/v0/dstu2/Observation/78496f26-82a3-5228-88ab-47ef91f1c6ce","resource":{"resourceType":"Observation","id":"78496f26-82a3-5228-88ab-47ef91f1c6ce","status":"final","category":{"coding":[{"system":"http://hl7.org/fhir/observation-category","code":"laboratory","display":"Laboratory"}]},"code":{"coding":[{"system":"http://loinc.org","code":"6298-4","display":"Potassium"}]},"subject":{"reference":"https://dev-api.va.gov/services/fhir/v0/dstu2/Patient/5000335","display":"Mr. Mariano761 Ruelas156"},"effectiveDateTime":"2008-09-05T10:47:37Z","issued":"2008-09-05T10:47:37Z","performer":[],"valueQuantity":{"value":5.084080897774635,"unit":"mmol/L","system":"http://unitsofmeasure.org","code":"mmol/L"}},"search":{"mode":"match"}},{"fullUrl":"https://dev-api.va.gov/services/fhir/v0/dstu2/Observation/d170911b-26e2-5317-b776-f485ead94739","resource":{"resourceType":"Observation","id":"d170911b-26e2-5317-b776-f485ead94739","status":"final","category":{"coding":[{"system":"http://hl7.org/fhir/observation-category","code":"laboratory","display":"Laboratory"}]},"code":{"coding":[{"system":"http://loinc.org","code":"2947-0","display":"Sodium"}]},"subject":{"reference":"https://dev-api.va.gov/services/fhir/v0/dstu2/Patient/5000335","display":"Mr. Mariano761 Ruelas156"},"effectiveDateTime":"2008-09-05T10:47:37Z","issued":"2008-09-05T10:47:37Z","performer":[],"valueQuantity":{"value":142.2530331632183,"unit":"mmol/L","system":"http://unitsofmeasure.org","code":"mmol/L"}},"search":{"mode":"match"}},{"fullUrl":"https://dev-api.va.gov/services/fhir/v0/dstu2/Observation/3528dfde-99fc-596c-a8c2-267e283ba85d","resource":{"resourceType":"Observation","id":"3528dfde-99fc-596c-a8c2-267e283ba85d","status":"final","category":{"coding":[{"system":"http://hl7.org/fhir/observation-category","code":"laboratory","display":"Laboratory"}]},"code":{"coding":[{"system":"http://loinc.org","code":"49765-1","display":"Calcium"}]},"subject":{"reference":"https://dev-api.va.gov/services/fhir/v0/dstu2/Patient/5000335","display":"Mr. Mariano761 Ruelas156"},"effectiveDateTime":"2008-09-05T10:47:37Z","issued":"2008-09-05T10:47:37Z","performer":[],"valueQuantity":{"value":9.151689059360976,"unit":"mg/dL","system":"http://unitsofmeasure.org","code":"mg/dL"}},"search":{"mode":"match"}},{"fullUrl":"https://dev-api.va.gov/services/fhir/v0/dstu2/Observation/3fc990a1-60ef-56a0-8a9d-3af476902432","resource":{"resourceType":"Observation","id":"3fc990a1-60ef-56a0-8a9d-3af476902432","status":"final","category":{"coding":[{"system":"http://hl7.org/fhir/observation-category","code":"laboratory","display":"Laboratory"}]},"code":{"coding":[{"system":"http://loinc.org","code":"38483-4","display":"Creatinine"}]},"subject":{"reference":"https://dev-api.va.gov/services/fhir/v0/dstu2/Patient/5000335","display":"Mr. Mariano761 Ruelas156"},"effectiveDateTime":"2008-09-05T10:47:37Z","issued":"2008-09-05T10:47:37Z","performer":[],"valueQuantity":{"value":3.0491356554675306,"unit":"mg/dL","system":"http://unitsofmeasure.org","code":"mg/dL"}},"search":{"mode":"match"}},{"fullUrl":"https://dev-api.va.gov/services/fhir/v0/dstu2/Observation/6f7d2e55-c570-51f6-9a95-59b8a911d359","resource":{"resourceType":"Observation","id":"6f7d2e55-c570-51f6-9a95-59b8a911d359","status":"final","category":{"coding":[{"system":"http://hl7.org/fhir/observation-category","code":"laboratory","display":"Laboratory"}]},"code":{"coding":[{"system":"http://loinc.org","code":"6299-2","display":"Urea Nitrogen"}]},"subject":{"reference":"https://dev-api.va.gov/services/fhir/v0/dstu2/Patient/5000335","display":"Mr. Mariano761 Ruelas156"},"effectiveDateTime":"2008-09-05T10:47:37Z","issued":"2008-09-05T10:47:37Z","performer":[],"valueQuantity":{"value":11.219756769127372,"unit":"mg/dL","system":"http://unitsofmeasure.org","code":"mg/dL"}},"search":{"mode":"match"}},{"fullUrl":"https://dev-api.va.gov/services/fhir/v0/dstu2/Observation/3a50d338-6624-5661-846b-3f2b65ed5160","resource":{"resourceType":"Observation","id":"3a50d338-6624-5661-846b-3f2b65ed5160","status":"final","category":{"coding":[{"system":"http://hl7.org/fhir/observation-category","code":"laboratory","display":"Laboratory"}]},"code":{"coding":[{"system":"http://loinc.org","code":"2339-0","display":"Glucose"}]},"subject":{"reference":"https://dev-api.va.gov/services/fhir/v0/dstu2/Patient/5000335","display":"Mr. Mariano761 Ruelas156"},"effectiveDateTime":"2008-09-05T10:47:37Z","issued":"2008-09-05T10:47:37Z","performer":[],"valueQuantity":{"value":114.52896356270597,"unit":"mg/dL","system":"http://unitsofmeasure.org","code":"mg/dL"}},"search":{"mode":"match"}},{"fullUrl":"https://dev-api.va.gov/services/fhir/v0/dstu2/Observation/892b717b-0d51-516c-88dc-7a7ee60de182","resource":{"resourceType":"Observation","id":"892b717b-0d51-516c-88dc-7a7ee60de182","status":"final","category":{"coding":[{"system":"http://hl7.org/fhir/observation-category","code":"vital-signs","display":"Vital Signs"}]},"code":{"coding":[{"system":"http://loinc.org","code":"72514-3","display":"Pain severity - 0-10 verbal numeric rating [#] - Reported"}]},"subject":{"reference":"https://dev-api.va.gov/services/fhir/v0/dstu2/Patient/5000335","display":"Mr. Mariano761 Ruelas156"},"effectiveDateTime":"2018-07-30T10:47:37Z","issued":"2018-07-30T10:47:37Z","performer":[],"valueQuantity":{"value":3.0}},"search":{"mode":"match"}},{"fullUrl":"https://dev-api.va.gov/services/fhir/v0/dstu2/Observation/c5b88796-374b-51ce-bebd-415ac5292f68","resource":{"resourceType":"Observation","id":"c5b88796-374b-51ce-bebd-415ac5292f68","status":"final","category":{"coding":[{"system":"http://hl7.org/fhir/observation-category","code":"vital-signs","display":"Vital Signs"}]},"code":{"coding":[{"system":"http://loinc.org","code":"72514-3","display":"Pain severity - 0-10 verbal numeric rating [#] - Reported"}]},"subject":{"reference":"https://dev-api.va.gov/services/fhir/v0/dstu2/Patient/5000335","display":"Mr. Mariano761 Ruelas156"},"effectiveDateTime":"2018-07-27T10:47:37Z","issued":"2018-07-27T10:47:37Z","performer":[],"valueQuantity":{"value":6.0}},"search":{"mode":"match"}},{"fullUrl":"https://dev-api.va.gov/services/fhir/v0/dstu2/Observation/c0977527-96ba-5a8a-b1ed-a78c063c9128","resource":{"resourceType":"Observation","id":"c0977527-96ba-5a8a-b1ed-a78c063c9128","status":"final","category":{"coding":[{"system":"http://hl7.org/fhir/observation-category","code":"vital-signs","display":"Vital Signs"}]},"code":{"coding":[{"system":"http://loinc.org","code":"72514-3","display":"Pain severity - 0-10 verbal numeric rating [#] - Reported"}]},"subject":{"reference":"https://dev-api.va.gov/services/fhir/v0/dstu2/Patient/5000335","display":"Mr. Mariano761 Ruelas156"},"effectiveDateTime":"2018-07-24T10:47:37Z","issued":"2018-07-24T10:47:37Z","performer":[],"valueQuantity":{"value":6.0}},"search":{"mode":"match"}},{"fullUrl":"https://dev-api.va.gov/services/fhir/v0/dstu2/Observation/b80ad689-bc8e-5984-a93d-7bedf6bda51f","resource":{"resourceType":"Observation","id":"b80ad689-bc8e-5984-a93d-7bedf6bda51f","status":"final","category":{"coding":[{"system":"http://hl7.org/fhir/observation-category","code":"vital-signs","display":"Vital Signs"}]},"code":{"coding":[{"system":"http://loinc.org","code":"72514-3","display":"Pain severity - 0-10 verbal numeric rating [#] - Reported"}]},"subject":{"reference":"https://dev-api.va.gov/services/fhir/v0/dstu2/Patient/5000335","display":"Mr. Mariano761 Ruelas156"},"effectiveDateTime":"2018-07-21T10:47:37Z","issued":"2018-07-21T10:47:37Z","performer":[],"valueQuantity":{"value":3.0}},"search":{"mode":"match"}},{"fullUrl":"https://dev-api.va.gov/services/fhir/v0/dstu2/Observation/72be09d3-4ce0-5d0c-a89a-8303c29dfb27","resource":{"resourceType":"Observation","id":"72be09d3-4ce0-5d0c-a89a-8303c29dfb27","status":"final","category":{"coding":[{"system":"http://hl7.org/fhir/observation-category","code":"vital-signs","display":"Vital Signs"}]},"code":{"coding":[{"system":"http://loinc.org","code":"72514-3","display":"Pain severity - 0-10 verbal numeric rating [#] - Reported"}]},"subject":{"reference":"https://dev-api.va.gov/services/fhir/v0/dstu2/Patient/5000335","display":"Mr. Mariano761 Ruelas156"},"effectiveDateTime":"2018-07-18T10:47:37Z","issued":"2018-07-18T10:47:37Z","performer":[],"valueQuantity":{"value":4.0}},"search":{"mode":"match"}},{"fullUrl":"https://dev-api.va.gov/services/fhir/v0/dstu2/Observation/5758f78b-1d0c-53a0-bafa-7028441f254a","resource":{"resourceType":"Observation","id":"5758f78b-1d0c-53a0-bafa-7028441f254a","status":"final","category":{"coding":[{"system":"http://hl7.org/fhir/observation-category","code":"vital-signs","display":"Vital Signs"}]},"code":{"coding":[{"system":"http://loinc.org","code":"72514-3","display":"Pain severity - 0-10 verbal numeric rating [#] - Reported"}]},"subject":{"reference":"https://dev-api.va.gov/services/fhir/v0/dstu2/Patient/5000335","display":"Mr. Mariano761 Ruelas156"},"effectiveDateTime":"2018-07-15T10:47:37Z","issued":"2018-07-15T10:47:37Z","performer":[],"valueQuantity":{"value":3.0}},"search":{"mode":"match"}},{"fullUrl":"https://dev-api.va.gov/services/fhir/v0/dstu2/Observation/293db004-13f3-5106-a59c-29d81ef56582","resource":{"resourceType":"Observation","id":"293db004-13f3-5106-a59c-29d81ef56582","status":"final","category":{"coding":[{"system":"http://hl7.org/fhir/observation-category","code":"vital-signs","display":"Vital Signs"}]},"code":{"coding":[{"system":"http://loinc.org","code":"72514-3","display":"Pain severity - 0-10 verbal numeric rating [#] - Reported"}]},"subject":{"reference":"https://dev-api.va.gov/services/fhir/v0/dstu2/Patient/5000335","display":"Mr. Mariano761 Ruelas156"},"effectiveDateTime":"2018-07-12T10:47:37Z","issued":"2018-07-12T10:47:37Z","performer":[],"valueQuantity":{"value":5.0}},"search":{"mode":"match"}},{"fullUrl":"https://dev-api.va.gov/services/fhir/v0/dstu2/Observation/8cba3453-aca2-5661-8090-6f77f99bd607","resource":{"resourceType":"Observation","id":"8cba3453-aca2-5661-8090-6f77f99bd607","status":"final","category":{"coding":[{"system":"http://hl7.org/fhir/observation-category","code":"vital-signs","display":"Vital Signs"}]},"code":{"coding":[{"system":"http://loinc.org","code":"72514-3","display":"Pain severity - 0-10 verbal numeric rating [#] - Reported"}]},"subject":{"reference":"https://dev-api.va.gov/services/fhir/v0/dstu2/Patient/5000335","display":"Mr. Mariano761 Ruelas156"},"effectiveDateTime":"2018-07-09T10:47:37Z","issued":"2018-07-09T10:47:37Z","performer":[],"valueQuantity":{"value":5.0}},"search":{"mode":"match"}},{"fullUrl":"https://dev-api.va.gov/services/fhir/v0/dstu2/Observation/eeddcf24-5eee-51b3-bc43-1943e26624cf","resource":{"resourceType":"Observation","id":"eeddcf24-5eee-51b3-bc43-1943e26624cf","status":"final","category":{"coding":[{"system":"http://hl7.org/fhir/observation-category","code":"vital-signs","display":"Vital Signs"}]},"code":{"coding":[{"system":"http://loinc.org","code":"72514-3","display":"Pain severity - 0-10 verbal numeric rating [#] - Reported"}]},"subject":{"reference":"https://dev-api.va.gov/services/fhir/v0/dstu2/Patient/5000335","display":"Mr. Mariano761 Ruelas156"},"effectiveDateTime":"2018-07-06T10:47:37Z","issued":"2018-07-06T10:47:37Z","performer":[],"valueQuantity":{"value":3.0}},"search":{"mode":"match"}}]}