{"resourceType":"Observation","id":"69aff656-ec1b-58d0-8b6d-e10813fad986","status":"final","category":{"coding":[{"system":"http://hl7.org/fhir/observation-category","code":"laboratory","display":"Laboratory"}]},"code":{"coding":[{"system":"http://loinc.org","code":"6298-4","display":"Potassium"}]},"subject":{"reference":"https://dev-api.va.gov/services/fhir/v0/dstu2/Patient/32000551","display":"Mr. Moshe758 Windler79"},"effectiveDateTime":"1998-01-12T16:17:33Z","issued":"1998-01-12T16:17:33Z","performer":[],"valueQuantity":{"value":4.730417065577469,"unit":"mmol/L","system":"http://unitsofmeasure.org","code":"mmol/L"}}