{"resourceType":"Observation","id":"f8697241-cff5-5f1b-9116-06341e89441a","status":"final","category":{"coding":[{"system":"http://hl7.org/fhir/observation-category","code":"laboratory","display":"Laboratory"}]},"code":{"coding":[{"system":"http://loinc.org","code":"2339-0","display":"Glucose"}]},"subject":{"reference":"https://dev-api.va.gov/services/fhir/v0/dstu2/Patient/32000551","display":"Mr. Moshe758 Windler79"},"effectiveDateTime":"1995-05-01T15:17:33Z","issued":"1995-05-01T15:17:33Z","performer":[],"valueQuantity":{"value":119.74952304019706,"unit":"mg/dL","system":"http://unitsofmeasure.org","code":"mg/dL"}}