{"resourceType":"Observation","id":"0444010e-0aed-510b-8cf5-e040f9190f8d","status":"final","category":{"coding":[{"system":"http://hl7.org/fhir/observation-category","code":"laboratory","display":"Laboratory"}]},"code":{"coding":[{"system":"http://loinc.org","code":"5797-6","display":"Ketones [Mass/volume] in Urine by Test strip"}]},"subject":{"reference":"https://dev-api.va.gov/services/fhir/v0/dstu2/Patient/25000285","display":"Mr. Porfirio146 Schmeler639"},"effectiveDateTime":"2010-03-05T05:39:20Z","issued":"2010-03-05T05:39:20Z","performer":[],"valueQuantity":{"value":19.630479657140924,"unit":"mg/dL","system":"http://unitsofmeasure.org","code":"mg/dL"}}