{"id":"f9423f46-433f-5674-be7a-6861500acdc3","resourceType":"Condition","patient":{"reference":"https://dev-api.va.gov/services/fhir/v0/dstu2/Patient/35000422","display":"Mr. Julius90 Gutmann970"},"dateRecorded":"1973-01-25","code":{"coding":[{"system":"https://snomed.info/sct","code":"38341003","display":"Hypertension"}],"text":"Hypertension"},"category":{"coding":[{"system":"http://argonaut.hl7.org","code":"problem","display":"Problem"}]},"clinicalStatus":"active","verificationStatus":"unknown","onsetDateTime":"1973-01-25T17:27:13Z"}