{"resourceType":"Observation","id":"9b576389-b098-518a-aa9d-71b0b6391075","status":"final","category":{"coding":[{"system":"http://hl7.org/fhir/observation-category","code":"laboratory","display":"Laboratory"}]},"code":{"coding":[{"system":"http://loinc.org","code":"2571-8","display":"Triglycerides"}]},"subject":{"reference":"https://dev-api.va.gov/services/fhir/v0/dstu2/Patient/39000049","display":"Mr. Harvey63 Kuhic920"},"effectiveDateTime":"2015-03-20T10:42:08Z","issued":"2015-03-20T10:42:08Z","performer":[],"valueQuantity":{"value":180.39045303563387,"unit":"mg/dL","system":"http://unitsofmeasure.org","code":"mg/dL"}}