{"resourceType":"Observation","id":"bb07ba0b-49fd-52ba-804c-d54a8c2ad837","status":"final","category":{"coding":[{"system":"http://hl7.org/fhir/observation-category","code":"laboratory","display":"Laboratory"}]},"code":{"coding":[{"system":"http://loinc.org","code":"2093-3","display":"Total Cholesterol"}]},"subject":{"reference":"https://dev-api.va.gov/services/fhir/v0/dstu2/Patient/39000049","display":"Mr. Harvey63 Kuhic920"},"effectiveDateTime":"2015-10-16T10:42:08Z","issued":"2015-10-16T10:42:08Z","performer":[],"valueQuantity":{"value":226.32131061333934,"unit":"mg/dL","system":"http://unitsofmeasure.org","code":"mg/dL"}}