{"resourceType":"Observation","id":"c56c7514-1ea2-5e64-9629-1b78713f2fff","status":"final","category":{"coding":[{"system":"http://hl7.org/fhir/observation-category","code":"laboratory","display":"Laboratory"}]},"code":{"coding":[{"system":"http://loinc.org","code":"5802-4","display":"Nitrite [Presence] in Urine by Test strip"}]},"subject":{"reference":"https://dev-api.va.gov/services/fhir/v0/dstu2/Patient/39000049","display":"Mr. Harvey63 Kuhic920"},"effectiveDateTime":"2015-08-10T10:42:08Z","issued":"2015-08-10T10:42:08Z","performer":[]}