{"id":"d02fccdc-8a3b-505b-ab6b-206b06f2a3cd","resourceType":"Condition","patient":{"reference":"https://dev-api.va.gov/services/fhir/v0/dstu2/Patient/4000751","display":"Mr. Dante562 Hayes766"},"dateRecorded":"1992-06-28","code":{"coding":[{"system":"https://snomed.info/sct","code":"26929004","display":"Alzheimer's disease (disorder)"}],"text":"Alzheimer's disease (disorder)"},"category":{"coding":[{"system":"http://argonaut.hl7.org","code":"problem","display":"Problem"}]},"clinicalStatus":"active","verificationStatus":"unknown","onsetDateTime":"1992-06-28T14:22:43Z"}