{"resourceType":"Observation","id":"e9493310-790a-59bc-bcaa-a83fb3e1fb73","status":"final","category":{"coding":[{"system":"http://hl7.org/fhir/observation-category","code":"laboratory","display":"Laboratory"}]},"code":{"coding":[{"system":"http://loinc.org","code":"789-8","display":"Erythrocytes [#/volume] in Blood by Automated coun"}]},"subject":{"reference":"https://dev-api.va.gov/services/fhir/v0/dstu2/Patient/25000126","display":"Mr. Lorenzo669 Valentín837"},"effectiveDateTime":"1999-09-19T00:02:59Z","issued":"1999-09-19T00:02:59Z","performer":[],"valueQuantity":{"value":4.024977604074986,"unit":"10*6/uL","system":"http://unitsofmeasure.org","code":"10*6/uL"}}