{"objectType":"Observation","objectVersion":1,"cdwId":"38233123:L","status":"final","category":"laboratory","code":{"coding":{"system":"http://loinc.org","code":"6298-4","display":"Potassium"}},"subject":{"type":"Patient","reference":"38000646","display":"Mr. Silas208 Little434"},"effectiveDateTime":"2009-03-03T17:35:41Z","issued":"2009-03-03T17:35:41Z","performer":[{"type":"Practitioner","reference":"305693","display":"Optional[DR.] THOMAS359 REYNOLDS206 Optional[PHD]"}],"valueQuantity":{"value":3.7228443532956437,"unit":"mmol/L","system":"http://unitsofmeasure.org","code":"mmol/L"}}