{"resourceType":"Observation","id":"3c8cf8df-d7b9-5a43-bfa0-863941640bda","status":"final","category":{"coding":[{"system":"http://hl7.org/fhir/observation-category","code":"laboratory","display":"Laboratory"}]},"code":{"coding":[{"system":"http://loinc.org","code":"33914-3","display":"Glomerular filtration rate/1.73 sq M.predicted"}]},"subject":{"reference":"https://dev-api.va.gov/services/fhir/v0/dstu2/Patient/38000527","display":"Mr. Nicholas495 Lueilwitz711"},"effectiveDateTime":"1990-02-06T05:42:43Z","issued":"1990-02-06T05:42:43Z","performer":[],"valueQuantity":{"value":7.579774824414292,"unit":"mL/min","system":"http://unitsofmeasure.org","code":"mL/min"}}