{"resourceType":"Observation","id":"94e8e5bc-7b7b-5fe8-ab0d-ae1649060d55","status":"final","category":{"coding":[{"system":"http://hl7.org/fhir/observation-category","code":"laboratory","display":"Laboratory"}]},"code":{"coding":[{"system":"http://loinc.org","code":"20565-8","display":"Carbon Dioxide"}]},"subject":{"reference":"https://dev-api.va.gov/services/fhir/v0/dstu2/Patient/10000271","display":"Mr. Cornelius968 Buckridge80"},"effectiveDateTime":"2013-08-27T13:36:53Z","issued":"2013-08-27T13:36:53Z","performer":[],"valueQuantity":{"value":23.965066370721573,"unit":"mmol/L","system":"http://unitsofmeasure.org","code":"mmol/L"}}