{"resourceType":"Observation","id":"3288b2f5-e2b9-5b6d-bbfc-0684bcc3d6af","status":"final","category":{"coding":[{"system":"http://hl7.org/fhir/observation-category","code":"laboratory","display":"Laboratory"}]},"code":{"coding":[{"system":"http://loinc.org","code":"2069-3","display":"Chloride"}]},"subject":{"reference":"https://dev-api.va.gov/services/fhir/v0/dstu2/Patient/43000498","display":"Mrs. Alex454 Kris249"},"effectiveDateTime":"2011-05-09T16:24:28Z","issued":"2011-05-09T16:24:28Z","performer":[],"valueQuantity":{"value":110.51354918104292,"unit":"mmol/L","system":"http://unitsofmeasure.org","code":"mmol/L"}}