{"resourceType":"Observation","id":"5993dc19-16cf-55c2-8325-8c8469502c2b","status":"final","category":{"coding":[{"system":"http://hl7.org/fhir/observation-category","code":"laboratory","display":"Laboratory"}]},"code":{"coding":[{"system":"http://loinc.org","code":"5792-7","display":"Glucose [Mass/volume] in Urine by Test strip"}]},"subject":{"reference":"https://dev-api.va.gov/services/fhir/v0/dstu2/Patient/17000098","display":"Mr. Freeman822 Prohaska837"},"effectiveDateTime":"2016-05-28T09:19:58Z","issued":"2016-05-28T09:19:58Z","performer":[],"valueQuantity":{"value":0.5374090873010113,"unit":"mg/dL","system":"http://unitsofmeasure.org","code":"mg/dL"}}