{"resourceType":"Observation","id":"fd09cb19-cbaa-5d62-a266-7232850ed26f","status":"final","category":{"coding":[{"system":"http://hl7.org/fhir/observation-category","code":"laboratory","display":"Laboratory"}]},"code":{"coding":[{"system":"http://loinc.org","code":"5794-3","display":"Hemoglobin [Presence] in Urine by Test strip"}]},"subject":{"reference":"https://dev-api.va.gov/services/fhir/v0/dstu2/Patient/42000354","display":"Mr. Gilberto712 Iglesias873"},"effectiveDateTime":"2014-02-17T01:13:38Z","issued":"2014-02-17T01:13:38Z","performer":[]}