{"objectType":"Observation","objectVersion":1,"cdwId":"23069879:L","status":"final","category":"laboratory","code":{"coding":{"system":"http://loinc.org","code":"2085-9","display":"High Density Lipoprotein Cholesterol"}},"subject":{"type":"Patient","reference":"23000219","display":"Mr. Taylor21 Mann644"},"effectiveDateTime":"2011-04-15T17:03:16Z","issued":"2011-04-15T17:03:16Z","performer":[{"type":"Organization","reference":"561596:I","display":"NEW AMSTERDAM CBOC"}],"valueQuantity":{"value":75.8560481928185,"unit":"mg/dL","system":"http://unitsofmeasure.org","code":"mg/dL"}}