{"objectType":"Observation","objectVersion":1,"cdwId":"43103158:L","status":"final","category":"laboratory","code":{"coding":{"system":"http://loinc.org","code":"1975-2","display":"Bilirubin.total [Mass/volume] in Serum or Plasma"}},"subject":{"type":"Patient","reference":"43000341","display":"Mr. Vicente970 Mata817"},"effectiveDateTime":"2009-05-22T09:12:34Z","issued":"2009-05-22T09:12:34Z","valueQuantity":{"value":0.9984941078888979,"unit":"mg/dL","system":"http://unitsofmeasure.org","code":"mg/dL"}}