{"id":"d2a1e4e1-70d2-57d2-a5b1-4016a5c3809f","resourceType":"Condition","patient":{"reference":"https://dev-api.va.gov/services/fhir/v0/dstu2/Patient/2000190","display":"Mr. Luis923 Mayer370"},"dateRecorded":"1987-08-27","code":{"coding":[{"system":"https://snomed.info/sct","code":"38341003","display":"Hypertension"}],"text":"Hypertension"},"category":{"coding":[{"system":"http://hl7.org/fhir/condition-category","code":"diagnosis","display":"Diagnosis"}]},"clinicalStatus":"active","verificationStatus":"unknown","onsetDateTime":"1987-08-27T11:00:04Z"}