{"resourceType":"Observation","id":"a06a0adc-fce4-5b82-9b68-aad1d0a1e86e","status":"final","category":{"coding":[{"system":"http://hl7.org/fhir/observation-category","code":"laboratory","display":"Laboratory"}]},"code":{"coding":[{"system":"http://loinc.org","code":"5778-6","display":"Color of Urine"}]},"subject":{"reference":"https://dev-api.va.gov/services/fhir/v0/dstu2/Patient/44","display":"Mr. Mariano761 Stark857"},"effectiveDateTime":"1972-12-31T15:42:56Z","issued":"1972-12-31T15:42:56Z","performer":[]}