{"objectType":"Observation","objectVersion":1,"cdwId":"2056239:L","status":"final","category":"laboratory","code":{"coding":{"system":"http://loinc.org","code":"777-3","display":"Platelets [#/volume] in Blood by Automated count"}},"subject":{"type":"Patient","reference":"2000167","display":"Mr. Jefferey580 Terry864"},"effectiveDateTime":"2009-03-23T09:14:31Z","issued":"2009-03-23T09:14:31Z","performer":[{"type":"Organization","reference":"561596:I","display":"NEW AMSTERDAM CBOC"},{"type":"Practitioner","reference":"294582","display":"Optional[DR.] JOHN248 SMITH811 Optional[MD]"}],"valueQuantity":{"value":198.87371270743634,"unit":"10*3/uL","system":"http://unitsofmeasure.org","code":"10*3/uL"}}