{"objectType":"DiagnosticReport","objectVersion":2,"cdwId":"1441:L","patient":{"type":"Patient","reference":"44","display":"Mr. Mariano761 Stark857"},"effectiveDateTime":"1972-04-29T14:42:56Z","issuedDateTime":"1972-04-29T14:42:56Z","accessionInstitution":null,"verifyingStaff":{"reference":null,"display":null},"topography":{"reference":null,"display":null},"visit":{"reference":null,"display":null},"orders":[],"results":[{"type":"Observation","reference":"11862:L","display":"Total Cholesterol"},{"type":"Observation","reference":"11863:L","display":"Triglycerides"},{"type":"Observation","reference":"11864:L","display":"Low Density Lipoprotein Cholesterol"},{"type":"Observation","reference":"11865:L","display":"High Density Lipoprotein Cholesterol"}]}