{"objectType":"Observation","objectVersion":1,"cdwId":"10209:L","status":"final","category":"laboratory","code":{"coding":{"system":"http://loinc.org","code":"6299-2","display":"Urea Nitrogen"}},"subject":{"type":"Patient","reference":"44","display":"Mr. Mariano761 Stark857"},"effectiveDateTime":"1967-03-25T15:42:56Z","issued":"1967-03-25T15:42:56Z","performer":[{"type":"Organization","reference":"457959:I","display":"LYONS VA MEDICAL CENTER"}],"valueQuantity":{"value":11.713697267769842,"unit":"mg/dL","system":"http://unitsofmeasure.org","code":"mg/dL"}}