{"resourceType":"Observation","id":"17e4b4f8-bddd-5095-a6c2-f24579d81523","status":"final","category":{"coding":[{"system":"http://hl7.org/fhir/observation-category","code":"laboratory","display":"Laboratory"}]},"code":{"coding":[{"system":"http://loinc.org","code":"5797-6","display":"Ketones [Mass/volume] in Urine by Test strip"}]},"subject":{"reference":"https://dev-api.va.gov/services/fhir/v0/dstu2/Patient/43000334","display":"Mr. Boris111 Keebler762"},"effectiveDateTime":"2015-02-02T01:14:00Z","issued":"2015-02-02T01:14:00Z","performer":[],"valueQuantity":{"value":11.045399610674911,"unit":"mg/dL","system":"http://unitsofmeasure.org","code":"mg/dL"}}