{"objectType":"Observation","objectVersion":1,"cdwId":"4225319:L","status":"final","category":"laboratory","code":{"coding":{"system":"http://loinc.org","code":"5811-5","display":"Specific gravity of Urine by Test strip"}},"subject":{"type":"Patient","reference":"4000751","display":"Mr. Dante562 Hayes766"},"effectiveDateTime":"2016-11-27T15:22:43Z","issued":"2016-11-27T15:22:43Z","valueQuantity":{"value":1.018496041008503,"unit":"{nominal}","system":"http://unitsofmeasure.org","code":"{nominal}"}}