{"objectType":"Condition","objectVersion":"1","cdwId":"21002758:D","patient":{"type":"Patient","reference":"21000265","display":"Mr. Alonso270 Jacobson885"},"recorder":{"type":"Practitioner","reference":"294582:S","display":"DR. JOHN248 SMITH811 MD"},"asserter":{"type":"Practitioner","reference":"294582:S","display":"DR. JOHN248 SMITH811 MD"},"dateRecorded":"2010-11-18","snomed":{"code":"263102004","display":"Fracture subluxation of wrist"},"icd":{"code":"S62.90XD","display":"Unspecified fracture of unspecified wrist and hand, subsequent encounter for fracture with routine healing","version":"10"},"category":"diagnosis","clinicalStatus":"inactive","verificationStatus":"refuted","onsetDateTime":"2010-11-18T05:28:36Z","abatementDateTime":"2010-12-18T05:28:36Z"}