{"resourceType":"Bundle","type":"searchset","total":7046,"link":[{"relation":"first","url":"https://dev-api.va.gov/services/fhir/v0/dstu2/Observation?patient=297&page=1&_count=15"},{"relation":"prev","url":"https://dev-api.va.gov/services/fhir/v0/dstu2/Observation?patient=297&page=155&_count=15"},{"relation":"self","url":"https://dev-api.va.gov/services/fhir/v0/dstu2/Observation?patient=297&page=156&_count=15"},{"relation":"next","url":"https://dev-api.va.gov/services/fhir/v0/dstu2/Observation?patient=297&page=157&_count=15"},{"relation":"last","url":"https://dev-api.va.gov/services/fhir/v0/dstu2/Observation?patient=297&page=470&_count=15"}],"entry":[{"fullUrl":"https://dev-api.va.gov/services/fhir/v0/dstu2/Observation/34917a16-666e-5245-a4f2-a95d764122f8","resource":{"resourceType":"Observation","id":"34917a16-666e-5245-a4f2-a95d764122f8","status":"final","category":{"coding":[{"system":"http://hl7.org/fhir/observation-category","code":"laboratory","display":"Laboratory"}]},"code":{"coding":[{"system":"http://loinc.org","code":"5797-6","display":"Ketones [Mass/volume] in Urine by Test strip"}]},"subject":{"reference":"https://dev-api.va.gov/services/fhir/v0/dstu2/Patient/297","display":"Mr. Lavern240 Hickle134"},"effectiveDateTime":"2014-02-12T06:33:11Z","issued":"2014-02-12T06:33:11Z","performer":[],"valueQuantity":{"value":15.657089157929025,"unit":"mg/dL","system":"http://unitsofmeasure.org","code":"mg/dL"}},"search":{"mode":"match"}},{"fullUrl":"https://dev-api.va.gov/services/fhir/v0/dstu2/Observation/b88342cd-f224-5f9c-960a-3b1836cf0c44","resource":{"resourceType":"Observation","id":"b88342cd-f224-5f9c-960a-3b1836cf0c44","status":"final","category":{"coding":[{"system":"http://hl7.org/fhir/observation-category","code":"laboratory","display":"Laboratory"}]},"code":{"coding":[{"system":"http://loinc.org","code":"5770-3","display":"Bilirubin.total [Presence] in Urine by Test strip"}]},"subject":{"reference":"https://dev-api.va.gov/services/fhir/v0/dstu2/Patient/297","display":"Mr. Lavern240 Hickle134"},"effectiveDateTime":"2014-02-12T06:33:11Z","issued":"2014-02-12T06:33:11Z","performer":[]},"search":{"mode":"match"}},{"fullUrl":"https://dev-api.va.gov/services/fhir/v0/dstu2/Observation/5433c48f-bd02-5af5-ae4c-448d6b6b5994","resource":{"resourceType":"Observation","id":"5433c48f-bd02-5af5-ae4c-448d6b6b5994","status":"final","category":{"coding":[{"system":"http://hl7.org/fhir/observation-category","code":"laboratory","display":"Laboratory"}]},"code":{"coding":[{"system":"http://loinc.org","code":"20505-4","display":"Bilirubin.total [Mass/volume] in Urine by Test str"}]},"subject":{"reference":"https://dev-api.va.gov/services/fhir/v0/dstu2/Patient/297","display":"Mr. Lavern240 Hickle134"},"effectiveDateTime":"2014-02-12T06:33:11Z","issued":"2014-02-12T06:33:11Z","performer":[],"valueQuantity":{"value":0.5829576678737519,"unit":"mg/dL","system":"http://unitsofmeasure.org","code":"mg/dL"}},"search":{"mode":"match"}},{"fullUrl":"https://dev-api.va.gov/services/fhir/v0/dstu2/Observation/dd7fdf53-67f4-5ccf-b289-b41fedc83c1d","resource":{"resourceType":"Observation","id":"dd7fdf53-67f4-5ccf-b289-b41fedc83c1d","status":"final","category":{"coding":[{"system":"http://hl7.org/fhir/observation-category","code":"laboratory","display":"Laboratory"}]},"code":{"coding":[{"system":"http://loinc.org","code":"25428-4","display":"Glucose [Presence] in Urine by Test strip"}]},"subject":{"reference":"https://dev-api.va.gov/services/fhir/v0/dstu2/Patient/297","display":"Mr. Lavern240 Hickle134"},"effectiveDateTime":"2014-02-12T06:33:11Z","issued":"2014-02-12T06:33:11Z","performer":[]},"search":{"mode":"match"}},{"fullUrl":"https://dev-api.va.gov/services/fhir/v0/dstu2/Observation/a62ff2c4-c3cb-533d-9220-c20efa257149","resource":{"resourceType":"Observation","id":"a62ff2c4-c3cb-533d-9220-c20efa257149","status":"final","category":{"coding":[{"system":"http://hl7.org/fhir/observation-category","code":"laboratory","display":"Laboratory"}]},"code":{"coding":[{"system":"http://loinc.org","code":"5792-7","display":"Glucose [Mass/volume] in Urine by Test strip"}]},"subject":{"reference":"https://dev-api.va.gov/services/fhir/v0/dstu2/Patient/297","display":"Mr. Lavern240 Hickle134"},"effectiveDateTime":"2014-02-12T06:33:11Z","issued":"2014-02-12T06:33:11Z","performer":[],"valueQuantity":{"value":2.4976141336389777,"unit":"mg/dL","system":"http://unitsofmeasure.org","code":"mg/dL"}},"search":{"mode":"match"}},{"fullUrl":"https://dev-api.va.gov/services/fhir/v0/dstu2/Observation/1f85c238-8a8a-51cc-b73a-a197f313ab6e","resource":{"resourceType":"Observation","id":"1f85c238-8a8a-51cc-b73a-a197f313ab6e","status":"final","category":{"coding":[{"system":"http://hl7.org/fhir/observation-category","code":"laboratory","display":"Laboratory"}]},"code":{"coding":[{"system":"http://loinc.org","code":"5778-6","display":"Color of Urine"}]},"subject":{"reference":"https://dev-api.va.gov/services/fhir/v0/dstu2/Patient/297","display":"Mr. Lavern240 Hickle134"},"effectiveDateTime":"2014-02-12T06:33:11Z","issued":"2014-02-12T06:33:11Z","performer":[]},"search":{"mode":"match"}},{"fullUrl":"https://dev-api.va.gov/services/fhir/v0/dstu2/Observation/614ac6c8-759c-57c7-8bfc-ed1b1b39fa3f","resource":{"resourceType":"Observation","id":"614ac6c8-759c-57c7-8bfc-ed1b1b39fa3f","status":"final","category":{"coding":[{"system":"http://hl7.org/fhir/observation-category","code":"laboratory","display":"Laboratory"}]},"code":{"coding":[{"system":"http://loinc.org","code":"32167-9","display":"Clarity of Urine"}]},"subject":{"reference":"https://dev-api.va.gov/services/fhir/v0/dstu2/Patient/297","display":"Mr. Lavern240 Hickle134"},"effectiveDateTime":"2014-02-12T06:33:11Z","issued":"2014-02-12T06:33:11Z","performer":[]},"search":{"mode":"match"}},{"fullUrl":"https://dev-api.va.gov/services/fhir/v0/dstu2/Observation/8aebc46c-0421-5722-8bf1-5c2331c04cb3","resource":{"resourceType":"Observation","id":"8aebc46c-0421-5722-8bf1-5c2331c04cb3","status":"final","category":{"coding":[{"system":"http://hl7.org/fhir/observation-category","code":"laboratory","display":"Laboratory"}]},"code":{"coding":[{"system":"http://loinc.org","code":"5767-9","display":"Appearance of Urine"}]},"subject":{"reference":"https://dev-api.va.gov/services/fhir/v0/dstu2/Patient/297","display":"Mr. Lavern240 Hickle134"},"effectiveDateTime":"2014-02-12T06:33:11Z","issued":"2014-02-12T06:33:11Z","performer":[]},"search":{"mode":"match"}},{"fullUrl":"https://dev-api.va.gov/services/fhir/v0/dstu2/Observation/6a6513d2-3841-56ec-a225-81d275f42a63","resource":{"resourceType":"Observation","id":"6a6513d2-3841-56ec-a225-81d275f42a63","status":"final","category":{"coding":[{"system":"http://hl7.org/fhir/observation-category","code":"laboratory","display":"Laboratory"}]},"code":{"coding":[{"system":"http://loinc.org","code":"5767-9","display":"Appearance of Urine"}]},"subject":{"reference":"https://dev-api.va.gov/services/fhir/v0/dstu2/Patient/297","display":"Mr. Lavern240 Hickle134"},"effectiveDateTime":"2014-02-12T06:33:11Z","issued":"2014-02-12T06:33:11Z","performer":[]},"search":{"mode":"match"}},{"fullUrl":"https://dev-api.va.gov/services/fhir/v0/dstu2/Observation/40f4279f-48da-5547-bb94-b0e5631ad099","resource":{"resourceType":"Observation","id":"40f4279f-48da-5547-bb94-b0e5631ad099","status":"final","category":{"coding":[{"system":"http://hl7.org/fhir/observation-category","code":"laboratory","display":"Laboratory"}]},"code":{"coding":[{"system":"http://loinc.org","code":"1920-8","display":"Aspartate aminotransferase [Enzymatic activity/vol"}]},"subject":{"reference":"https://dev-api.va.gov/services/fhir/v0/dstu2/Patient/297","display":"Mr. Lavern240 Hickle134"},"effectiveDateTime":"2014-02-12T06:33:11Z","issued":"2014-02-12T06:33:11Z","performer":[],"valueQuantity":{"value":26.96745645828392,"unit":"U/L","system":"http://unitsofmeasure.org","code":"U/L"}},"search":{"mode":"match"}},{"fullUrl":"https://dev-api.va.gov/services/fhir/v0/dstu2/Observation/a364c461-0184-542c-986f-f614a0da629c","resource":{"resourceType":"Observation","id":"a364c461-0184-542c-986f-f614a0da629c","status":"final","category":{"coding":[{"system":"http://hl7.org/fhir/observation-category","code":"laboratory","display":"Laboratory"}]},"code":{"coding":[{"system":"http://loinc.org","code":"1742-6","display":"Alanine aminotransferase [Enzymatic activity/volum"}]},"subject":{"reference":"https://dev-api.va.gov/services/fhir/v0/dstu2/Patient/297","display":"Mr. Lavern240 Hickle134"},"effectiveDateTime":"2014-02-12T06:33:11Z","issued":"2014-02-12T06:33:11Z","performer":[],"valueQuantity":{"value":56.866262080842176,"unit":"U/L","system":"http://unitsofmeasure.org","code":"U/L"}},"search":{"mode":"match"}},{"fullUrl":"https://dev-api.va.gov/services/fhir/v0/dstu2/Observation/991c0038-0c7d-5b45-bd68-53b8d029d4ee","resource":{"resourceType":"Observation","id":"991c0038-0c7d-5b45-bd68-53b8d029d4ee","status":"final","category":{"coding":[{"system":"http://hl7.org/fhir/observation-category","code":"laboratory","display":"Laboratory"}]},"code":{"coding":[{"system":"http://loinc.org","code":"6768-6","display":"Alkaline phosphatase [Enzymatic activity/volume] i"}]},"subject":{"reference":"https://dev-api.va.gov/services/fhir/v0/dstu2/Patient/297","display":"Mr. Lavern240 Hickle134"},"effectiveDateTime":"2014-02-12T06:33:11Z","issued":"2014-02-12T06:33:11Z","performer":[],"valueQuantity":{"value":103.67152320219175,"unit":"U/L","system":"http://unitsofmeasure.org","code":"U/L"}},"search":{"mode":"match"}},{"fullUrl":"https://dev-api.va.gov/services/fhir/v0/dstu2/Observation/94c32ce9-c234-51b7-bd6a-874ad0b6bdef","resource":{"resourceType":"Observation","id":"94c32ce9-c234-51b7-bd6a-874ad0b6bdef","status":"final","category":{"coding":[{"system":"http://hl7.org/fhir/observation-category","code":"laboratory","display":"Laboratory"}]},"code":{"coding":[{"system":"http://loinc.org","code":"1975-2","display":"Bilirubin.total [Mass/volume] in Serum or Plasma"}]},"subject":{"reference":"https://dev-api.va.gov/services/fhir/v0/dstu2/Patient/297","display":"Mr. Lavern240 Hickle134"},"effectiveDateTime":"2014-02-12T06:33:11Z","issued":"2014-02-12T06:33:11Z","performer":[],"valueQuantity":{"value":0.1839689205871173,"unit":"mg/dL","system":"http://unitsofmeasure.org","code":"mg/dL"}},"search":{"mode":"match"}},{"fullUrl":"https://dev-api.va.gov/services/fhir/v0/dstu2/Observation/4af95fe0-2b28-5bc3-ae98-b1ac2cf673c9","resource":{"resourceType":"Observation","id":"4af95fe0-2b28-5bc3-ae98-b1ac2cf673c9","status":"final","category":{"coding":[{"system":"http://hl7.org/fhir/observation-category","code":"laboratory","display":"Laboratory"}]},"code":{"coding":[{"system":"http://loinc.org","code":"10834-0","display":"Globulin [Mass/volume] in Serum by calculation"}]},"subject":{"reference":"https://dev-api.va.gov/services/fhir/v0/dstu2/Patient/297","display":"Mr. Lavern240 Hickle134"},"effectiveDateTime":"2014-02-12T06:33:11Z","issued":"2014-02-12T06:33:11Z","performer":[],"valueQuantity":{"value":2.679957187738689,"unit":"g/L","system":"http://unitsofmeasure.org","code":"g/L"}},"search":{"mode":"match"}},{"fullUrl":"https://dev-api.va.gov/services/fhir/v0/dstu2/Observation/4fa60487-799b-504e-a8e3-93487d3eea10","resource":{"resourceType":"Observation","id":"4fa60487-799b-504e-a8e3-93487d3eea10","status":"final","category":{"coding":[{"system":"http://hl7.org/fhir/observation-category","code":"laboratory","display":"Laboratory"}]},"code":{"coding":[{"system":"http://loinc.org","code":"1751-7","display":"Albumin [Mass/volume] in Serum or Plasma"}]},"subject":{"reference":"https://dev-api.va.gov/services/fhir/v0/dstu2/Patient/297","display":"Mr. Lavern240 Hickle134"},"effectiveDateTime":"2014-02-12T06:33:11Z","issued":"2014-02-12T06:33:11Z","performer":[],"valueQuantity":{"value":4.047369516530897,"unit":"g/dL","system":"http://unitsofmeasure.org","code":"g/dL"}},"search":{"mode":"match"}}]}