{"objectType":"Observation","objectVersion":1,"cdwId":"5912:L","status":"final","category":"laboratory","code":{"coding":{"system":"http://loinc.org","code":"20565-8","display":"Carbon Dioxide"}},"subject":{"type":"Patient","reference":"38","display":"Mr. Darryl392 Hartmann983"},"effectiveDateTime":"2009-08-26T18:16:07Z","issued":"2009-08-26T18:16:07Z","performer":[{"type":"Organization","reference":"568060:I","display":"WASHINGTON VA MEDICAL CENTER"},{"type":"Practitioner","reference":"294582","display":"Optional[DR.] JOHN248 SMITH811 Optional[MD]"}],"valueQuantity":{"value":20.918310842287863,"unit":"mmol/L","system":"http://unitsofmeasure.org","code":"mmol/L"}}